histoptimizer/__init__.py
histoptimizer/benchmark.py
histoptimizer/cli.py
histoptimizer/cuda.py
histoptimizer/historical/__init__.py
histoptimizer/historical/cuda_2.py
histoptimizer/historical/enumerate.py
histoptimizer/historical/recursive.py
histoptimizer/historical/recursive_cache.py
histoptimizer/numba_optimizer.py
histoptimizer-1.0.dist-info/entry_points.txt
histoptimizer-1.0.dist-info/LICENSE
histoptimizer-1.0.dist-info/METADATA
histoptimizer-1.0.dist-info/WHEEL
histoptimizer-1.0.dist-info/RECORD
