Metadata-Version: 2.1
Name: histoptimizer
Version: 1.0
Summary: A library for creating even partitions of ordered items.
Home-page: https://histoptimizer.org/
License: BSD 0-Clause License
Keywords: cuda,numba,dynamic programming,partition
Author: Kelly Joyner
Author-email: de@lusion.org
Requires-Python: >=3.8.1,<4.0.0
Classifier: Development Status :: 4 - Beta
Classifier: License :: OSI Approved :: BSD License
Classifier: License :: Other/Proprietary License
Classifier: Programming Language :: Python :: 3
Classifier: Programming Language :: Python :: 3.9
Classifier: Programming Language :: Python :: 3.10
Classifier: Programming Language :: Python :: 3.11
Classifier: Programming Language :: Python :: 3
Classifier: Topic :: Utilities
Requires-Dist: click (>=8,<9)
Requires-Dist: numba (>=0.56,<0.57)
Requires-Dist: numpy (>=1,<2)
Requires-Dist: pandas (>=1.5,<2.0)
Project-URL: Documentation, https://histoptimizer.org/
Project-URL: Repository, https://github.com/delusionary/histoptimizer
